tomcru/__init__.py
tomcru/appbuilders/envmapping.py
tomcru/appbuilders/faas/InjectableAppBase.py
tomcru/appbuilders/faas/sam_app/SamAppBuilder.py
tomcru/appbuilders/faas/sam_app/__init__.py
tomcru/appbuilders/faas/static_app/StaticAppBuilder.py
tomcru/appbuilders/faas/static_app/__init__.py
tomcru/cfgparsers/BaseCfgParser.py
tomcru/cfgparsers/EnvParser.py
tomcru/cfgparsers/MergeCfgParser.py
tomcru/cfgparsers/SwaggerCfgParser.py
tomcru/cfgparsers/__init__.py
tomcru/core/__init__.py
tomcru/core/cfg/api.py
tomcru/core/cfg/authorizers.py
tomcru/core/cfg/integrations.py
tomcru/core/cfg/proj.py
tomcru/core/logger.py
tomcru/core/modloader.py
tomcru/core/obj_store.py
tomcru/core/project.py
tomcru/core/servmgr.py
tomcru/core/utils/MyMetaLoader.py
tomcru/core/utils/__init__.py
tomcru/core/utils/toml_custom.py
tomcru/core/utils/yaml_custom.py
tomcru/etc/proxies/aws-sdk/index.js
tomcru/etc/proxies/aws-sdk/package.json
tomcru/etc/proxies/aws-sdk/proxylib.js
tomcru/etc/proxies/aws-sdk/serv/ddb.js
tomcru/etc/proxies/t_proxy.js
tomcru/services/ServiceBase.py
tomcru/services/__init__.py
tomcru/services/aws/__init__.py
tomcru/services/aws/hosted/apigw/__init__.py
tomcru/services/aws/hosted/apigw/api_shared/ApiGWBuilderBase.py
tomcru/services/aws/hosted/apigw/api_shared/__init__.py
tomcru/services/aws/hosted/apigw/api_shared/integration/ExternalLambdaAuthorizerIntegration.py
tomcru/services/aws/hosted/apigw/api_shared/integration/FlaskCorsAfterRequestHook.py
tomcru/services/aws/hosted/apigw/api_shared/integration/LambdaAuthorizerIntegration.py
tomcru/services/aws/hosted/apigw/api_shared/integration/OIDCAuthorizerIntegration.py
tomcru/services/aws/hosted/apigw/api_shared/integration/TomcruApiGWHttpIntegration.py
tomcru/services/aws/hosted/apigw/api_shared/integration/__init__.py
tomcru/services/aws/hosted/apigw/flask_b/ApiGWFlaskBuilder.py
tomcru/services/aws/hosted/apigw/flask_b/__init__.py
tomcru/services/aws/hosted/apigw/flask_b/controllers/EmeProxyController.py
tomcru-0.2.11.dist-info/LICENSE
tomcru-0.2.11.dist-info/METADATA
tomcru-0.2.11.dist-info/WHEEL
tomcru-0.2.11.dist-info/RECORD
