Metadata-Version: 2.1
Name: tomcru
Version: 0.2.11
Summary: Serverless app framework
Author: Rajmund Csombordi
Author-email: rajmund.csombordi@hotmail.com
Requires-Python: >=3.10,<4.0
Classifier: Programming Language :: Python :: 3
Classifier: Programming Language :: Python :: 3.10
Classifier: Programming Language :: Python :: 3.11
Requires-Dist: apispec (>=6.3,<7.0)
Requires-Dist: botocore (>=1.29,<2.0)
Requires-Dist: deepmerge (>=1.1.0,<2.0.0)
Requires-Dist: flask-swagger-ui (>=4.11,<5.0)
Requires-Dist: flatten-json (>=0.1.13,<0.2.0)
Requires-Dist: openapi-spec-validator (>=0.5,<1.0)
Requires-Dist: prance (>=0.22,<1.0)
Requires-Dist: pyjwt (>=2.6,<3.0)
Requires-Dist: pyyaml (>=6.0,<7.0)
Requires-Dist: requests (>=2.28,<3.0)
Requires-Dist: tabulate (>=0.9.0,<0.10.0)
Requires-Dist: tomcru-jerry (>=0.1.3,<0.2.0)
